kwola/__init__.py
kwola/bin/__init__.py
kwola/bin/benchmark_neural_network.py
kwola/bin/create_kros3_experiment.py
kwola/bin/full_internal_test_suite.py
kwola/bin/initialize.py
kwola/bin/install_proxy_cert.py
kwola/bin/main.py
kwola/bin/rapid_local_test_suite.py
kwola/bin/regenerate_charts.py
kwola/bin/reset.py
kwola/bin/run_multiple.py
kwola/bin/run_test_step.py
kwola/bin/run_train_step.py
kwola/bin/test_chromedriver.py
kwola/bin/test_ffmpeg.py
kwola/bin/test_installation.py
kwola/bin/test_javascript_rewriting.py
kwola/bin/test_neural_network.py
kwola/bin/train_agent.py
kwola/bin/website_check.py
kwola/components/__init__.py
kwola/components/agents/DeepLearningAgent.py
kwola/components/agents/SymbolMapper.py
kwola/components/agents/TraceNet.py
kwola/components/agents/__init__.py
kwola/components/environments/WebEnvironment.py
kwola/components/environments/WebEnvironmentSession.py
kwola/components/environments/__init__.py
kwola/components/managers/TestingManager.py
kwola/components/managers/TestingStepManager.py
kwola/components/managers/TrainingManager.py
kwola/components/managers/__init__.py
kwola/components/plugins/__init__.py
kwola/components/plugins/base/ProxyPluginBase.py
kwola/components/plugins/base/TestingStepPluginBase.py
kwola/components/plugins/base/TrainingStepPluginBase.py
kwola/components/plugins/base/WebEnvironmentPluginBase.py
kwola/components/plugins/base/__init__.py
kwola/components/plugins/core/CreateLocalBugObjects.py
kwola/components/plugins/core/GenerateAnnotatedVideos.py
kwola/components/plugins/core/GenerateDebugVideos.py
kwola/components/plugins/core/HTMLRewriter.py
kwola/components/plugins/core/JSRewriter.py
kwola/components/plugins/core/LogSessionActionExecutionTimes.py
kwola/components/plugins/core/LogSessionRewards.py
kwola/components/plugins/core/PrecomputeSessionsForSampleCache.py
kwola/components/plugins/core/RecordAllPaths.py
kwola/components/plugins/core/RecordBranchTrace.py
kwola/components/plugins/core/RecordCursorAtAction.py
kwola-0.1.52.dist-info/LICENSE
kwola-0.1.52.dist-info/METADATA
kwola-0.1.52.dist-info/WHEEL
kwola-0.1.52.dist-info/entry_points.txt
kwola-0.1.52.dist-info/top_level.txt
kwola-0.1.52.dist-info/RECORD
