Metadata-Version: 2.1
Name: kwola
Version: 0.1.52
Summary: Kwola makes an AI powered tool for finding bugs in software
Home-page: https://kwola.io/
Author: Bradley Arsenault
Author-email: brad@kwola.io
License: UNKNOWN
Keywords: torch pytorch artificial intelligence
Platform: UNKNOWN
Classifier: Programming Language :: Python
Classifier: Framework :: Pyramid
Requires-Python: >=3.6
Requires-Dist: mitmproxy
Requires-Dist: mongoengine
Requires-Dist: numpy
Requires-Dist: opencv-python
Requires-Dist: pandas
Requires-Dist: psutil
Requires-Dist: questionary
Requires-Dist: requests
Requires-Dist: scikit-image
Requires-Dist: scikit-learn
Requires-Dist: scipy
Requires-Dist: selenium
Requires-Dist: testtools
Requires-Dist: torch
Requires-Dist: filetype
Requires-Dist: billiard
Requires-Dist: wheel
Requires-Dist: StringDist
Requires-Dist: bs4
Requires-Dist: google-cloud-storage
Requires-Dist: Faker
Requires-Dist: giturlparse
Requires-Dist: edlib
Requires-Dist: python-snappy
